{"GlobalPropertiesHash":"7PZuqqoagqtVBZLmw8q4w1mhqPoWuxx+tlklwRL9oR4=","FingerprintPatternsHash":"gq3WsqcKBUGTSNle7RKKyXRIwh7M8ccEqOqYvIzoM04=","PropertyOverridesHash":"8ZRc1sGeVrPBx4lD717BgRaQekyh78QKV9SKsdt638U=","InputHashes":["4CqgHHXe5qkoySzd33MRT/PEWlq9ID33kOPQJZ9a9BM=","X6dahOXloZawGwvlpE8HOZNY0b28aLT/uejVQCZb/tQ=","c\u002BUVnvlIM2TjfDfwbOQqz\u002BVlbATcVKQG7tBI8VZIk7A="],"CachedAssets":{"4CqgHHXe5qkoySzd33MRT/PEWlq9ID33kOPQJZ9a9BM=":{"Identity":"c:\\Users\\ameri\\Desktop\\Pasantias geotec - copia\\gt-chat\\server\\wwwroot\\README.txt","SourceId":"server","SourceType":"Discovered","ContentRoot":"c:\\Users\\ameri\\Desktop\\Pasantias geotec - copia\\gt-chat\\server\\wwwroot\\","BasePath":"_content/server","RelativePath":"README#[.{fingerprint}]?.txt","AssetKind":"All","AssetMode":"All","AssetRole":"Primary","AssetMergeBehavior":null,"AssetMergeSource":"","RelatedAsset":null,"AssetTraitName":null,"AssetTraitValue":null,"Fingerprint":"mc9yyc6rr6","Integrity":"KmribQDAEDmSzgGyguqL3xK4UZCsz/hWYqKzj3kJhWE=","CopyToOutputDirectory":"Never","CopyToPublishDirectory":"PreserveNewest","OriginalItemSpec":"wwwroot\\README.txt","FileLength":88,"LastWriteTime":"2025-08-29T09:33:15.9524951+00:00"}},"CachedCopyCandidates":{}}